{

"root": {
    "FlexStyle": {
        "dims": {"width": {"Vw": 100.0}, "height": {"Vh": 100.0}},
        "content": {"justify_main": "SpaceEvenly", "justify_cross": "Center"}
    },

    "button": {
        "AbsoluteStyle": {
            "dims": {"top": "Auto", "left": "Auto"},
            "content": {"justify_main": "Center", "justify_cross": "Center"}
        },
        "BgColor": [{"Hsla": {"hue": 80.0, "saturation": 0.7, "lightness": 0.4, "alpha": 0.8}}],

        "text": {
            "FlexStyle": {
                "flex": {"margin": {"top": {"Px": 10.0}, "bottom": {"Px": 10.0}, "left": {"Px": 10.0}, "right": {"Px": 10.0}}}
            }
        }
    }
}

}
